{
  "updatedAt": "2026-07-23T11:27:49.805Z",
  "source": "Wirawan",
  "dataSource": "Dashboard",
  "workbook": "Doff Management rev.1.xlsx",
  "si": "Wirawan",
  "siCell": "BV5",
  "siValue": "Wirawan",
  "siReadMode": "BV5 getValue before date/shift update",
  "dateSelector": "7/23/2026",
  "shiftSelector": "AS",
  "productionDateSerial": 46226,
  "productionDateText": "7/23/2026",
  "shiftSet": "AS",
  "shifts": {
    "MS": {
      "cm3": [
        {
          "key": "20260723-MS-HE 2-PLAN",
          "date": "7/23/2026",
          "shift": "",
          "cluster": "CM3",
          "group": "Alidra Heli",
          "mc": "HE 2",
          "jenis": "GF",
          "plan": "06:00",
          "doff": "06:00",
          "start": "07:15",
          "code": "",
          "std": "97.3",
          "dt_mc": "75",
          "dt_proc": "75",
          "loss": "22.3",
          "pct_loss": "4.7%",
          "overlap": "360",
          "ket": "GF. Awal (No 86-96 1x doff) + C + Jalan ½ Length",
          "status": "Actual",
          "eff": "22.9%"
        },
        {
          "key": "20260723-MS-HE 1-PLAN",
          "date": "7/23/2026",
          "shift": "",
          "cluster": "CM3",
          "group": "Alidra Heli",
          "mc": "HE 1",
          "jenis": "GF",
          "plan": "10:15",
          "doff": "10:15",
          "start": "12:00",
          "code": "",
          "std": "97.3",
          "dt_mc": "105",
          "dt_proc": "105",
          "loss": "-7.7",
          "pct_loss": "-1.6%",
          "overlap": "830",
          "ket": "D + GF ½ MC (1x doff) + C + P. Istirahat + Briefing",
          "status": "Actual",
          "eff": "-7.9%"
        },
        {
          "key": "20260723-MS-HE 8-PLAN",
          "date": "7/23/2026",
          "shift": "",
          "cluster": "CM3",
          "group": "Alidra Heli",
          "mc": "HE 8",
          "jenis": "D",
          "plan": "12:30",
          "doff": "12:30",
          "start": "13:15",
          "code": "",
          "std": "17.8",
          "dt_mc": "45",
          "dt_proc": "45",
          "loss": "-27.2",
          "pct_loss": "-5.7%",
          "overlap": "90",
          "ket": "D + C + HB (68 spdl)",
          "status": "Actual",
          "eff": "-153.1%"
        },
        {
          "key": "20260723-MS-HE 6-PLAN",
          "date": "7/23/2026",
          "shift": "",
          "cluster": "CM3",
          "group": "Alidra Heli",
          "mc": "HE 6",
          "jenis": "GF",
          "plan": "13:30",
          "doff": "13:30",
          "start": "14:00",
          "code": "L",
          "std": "97.3",
          "dt_mc": "30",
          "dt_proc": "",
          "loss": "",
          "pct_loss": "",
          "overlap": "",
          "ket": "D. Akhir (Belum Doff)",
          "status": "Actual",
          "eff": ""
        },
        {
          "key": "20260723-MS-DT 12-PLAN",
          "date": "7/23/2026",
          "shift": "",
          "cluster": "CM3",
          "group": "DT New",
          "mc": "DT 12",
          "jenis": "D",
          "plan": "11:10",
          "doff": "11:10",
          "start": "11:35",
          "code": "",
          "std": "13.5",
          "dt_mc": "25",
          "dt_proc": "25",
          "loss": "-11.5",
          "pct_loss": "-2.4%",
          "overlap": "",
          "ket": "Doff + C + Hb + briefing",
          "status": "Actual",
          "eff": "-85.8%"
        },
        {
          "key": "20260723-MS-L 16-PLAN",
          "date": "7/23/2026",
          "shift": "",
          "cluster": "CM3",
          "group": "NL",
          "mc": "L 16",
          "jenis": "GF",
          "plan": "11:30",
          "doff": "11:30",
          "start": "12:00",
          "code": "",
          "std": "35.8",
          "dt_mc": "30",
          "dt_proc": "30",
          "loss": "5.8",
          "pct_loss": "1.2%",
          "overlap": "",
          "ket": "D + GF + C",
          "status": "Actual",
          "eff": "16.2%"
        }
      ],
      "cm6": [
        {
          "key": "20260723-MS-Delta 11-PLAN",
          "date": "7/23/2026",
          "shift": "MS",
          "cluster": "CM6",
          "group": "TBR Delta",
          "mc": "Delta 11",
          "jenis": "GF",
          "plan": "08:00",
          "doff": "08:10",
          "start": "09:00",
          "code": "",
          "std": "37.1",
          "dt_mc": "50",
          "dt_proc": "50",
          "loss": "-13.0",
          "pct_loss": "-2.7%",
          "overlap": "350",
          "ket": "Doff + Gf + R",
          "status": "Actual",
          "eff": "-35.0%"
        },
        {
          "key": "20260723-MS-Delta 5-PLAN",
          "date": "7/23/2026",
          "shift": "MS",
          "cluster": "CM6",
          "group": "TBR Delta",
          "mc": "Delta 5",
          "jenis": "GF",
          "plan": "08:30",
          "doff": "08:25",
          "start": "10:35",
          "code": "",
          "std": "112.8",
          "dt_mc": "130",
          "dt_proc": "95",
          "loss": "17.8",
          "pct_loss": "3.7%",
          "overlap": "305",
          "ket": "Doff + Gf (1xdoff) + dahulukan no.11 + p.istirahat + R",
          "status": "Actual",
          "eff": "15.8%"
        },
        {
          "key": "20260723-MS-Delta 13-PLAN",
          "date": "7/23/2026",
          "shift": "MS",
          "cluster": "CM6",
          "group": "TBR Delta",
          "mc": "Delta 13",
          "jenis": "GF",
          "plan": "10:00",
          "doff": "09:35",
          "start": "11:30",
          "code": "",
          "std": "37.1",
          "dt_mc": "115",
          "dt_proc": "55",
          "loss": "-18.0",
          "pct_loss": "-3.7%",
          "overlap": "",
          "ket": "Doff + Gf + Dahulukan no.5 + cleaning m/c + R",
          "status": "Actual",
          "eff": "-48.4%"
        },
        {
          "key": "20260723-MS-Delta 4-PLAN",
          "date": "7/23/2026",
          "shift": "MS",
          "cluster": "CM6",
          "group": "TBR Delta",
          "mc": "Delta 4",
          "jenis": "GF",
          "plan": "10:30",
          "doff": "10:30",
          "start": "13:30",
          "code": "",
          "std": "112.8",
          "dt_mc": "180",
          "dt_proc": "120",
          "loss": "-7.2",
          "pct_loss": "-1.5%",
          "overlap": "",
          "ket": "Doff + Gf + Dahulukan no.13 + G.tensioner LMN + R",
          "status": "Actual",
          "eff": "-6.4%"
        },
        {
          "key": "20260723-MS-Delta 10-PLAN",
          "date": "7/23/2026",
          "shift": "MS",
          "cluster": "CM6",
          "group": "TBR Delta",
          "mc": "Delta 10",
          "jenis": "GF",
          "plan": "13:30",
          "doff": "13:15",
          "start": "14:00",
          "code": "L",
          "std": "37.1",
          "dt_mc": "45",
          "dt_proc": "",
          "loss": "",
          "pct_loss": "",
          "overlap": "",
          "ket": "Doff + Gf + Tf(rewending)",
          "status": "Actual",
          "eff": ""
        },
        {
          "key": "20260723-MS-DT 5-PLAN",
          "date": "7/23/2026",
          "shift": "MS",
          "cluster": "CM6",
          "group": "TBR DT",
          "mc": "DT 5",
          "jenis": "D",
          "plan": "06:05",
          "doff": "06:05",
          "start": "06:30",
          "code": "",
          "std": "13.5",
          "dt_mc": "25",
          "dt_proc": "25",
          "loss": "-11.5",
          "pct_loss": "-2.4%",
          "overlap": "",
          "ket": "Doff Criling hb 18 patroling awal",
          "status": "Actual",
          "eff": "-85.8%"
        },
        {
          "key": "20260723-MS-DT 7-PLAN",
          "date": "7/23/2026",
          "shift": "MS",
          "cluster": "CM6",
          "group": "TBR DT",
          "mc": "DT 7",
          "jenis": "D",
          "plan": "07:30",
          "doff": "07:25",
          "start": "07:35",
          "code": "",
          "std": "13.5",
          "dt_mc": "10",
          "dt_proc": "10",
          "loss": "3.5",
          "pct_loss": "0.7%",
          "overlap": "395",
          "ket": "Doff Criling hb 13 Briefing",
          "status": "Actual",
          "eff": "25.7%"
        },
        {
          "key": "20260723-MS-DT 2-PLAN",
          "date": "7/23/2026",
          "shift": "MS",
          "cluster": "CM6",
          "group": "TBR DT",
          "mc": "DT 2",
          "jenis": "GF",
          "plan": "06:35",
          "doff": "06:35",
          "start": "08:25",
          "code": "",
          "std": "82.7",
          "dt_mc": "110",
          "dt_proc": "50",
          "loss": "32.7",
          "pct_loss": "6.8%",
          "overlap": "1295",
          "ket": "Doff Gf dah dt 7",
          "status": "Actual",
          "eff": "39.6%"
        },
        {
          "key": "20260723-MS-DT 3-PLAN",
          "date": "7/23/2026",
          "shift": "MS",
          "cluster": "CM6",
          "group": "TBR DT",
          "mc": "DT 3",
          "jenis": "GF",
          "plan": "11:20",
          "doff": "11:25",
          "start": "12:35",
          "code": "",
          "std": "82.7",
          "dt_mc": "70",
          "dt_proc": "70",
          "loss": "12.7",
          "pct_loss": "2.7%",
          "overlap": "",
          "ket": "Doff  Gf dah dt 4",
          "status": "Actual",
          "eff": "15.4%"
        },
        {
          "key": "20260723-MS-DT 6-PLAN",
          "date": "7/23/2026",
          "shift": "MS",
          "cluster": "CM6",
          "group": "TBR DT",
          "mc": "DT 6",
          "jenis": "GF",
          "plan": "13:25",
          "doff": "13:35",
          "start": "14:00",
          "code": "L",
          "std": "82.7",
          "dt_mc": "25",
          "dt_proc": "",
          "loss": "",
          "pct_loss": "",
          "overlap": "",
          "ket": "Doff Gf (2× feeding)",
          "status": "Actual",
          "eff": ""
        },
        {
          "key": "20260723-MS-DT 2-PLAN",
          "date": "7/23/2026",
          "shift": "MS",
          "cluster": "CM6",
          "group": "TBR DT",
          "mc": "DT 2",
          "jenis": "GF",
          "plan": "06:35",
          "doff": "",
          "start": "",
          "code": "",
          "std": "82.7",
          "dt_mc": "",
          "dt_proc": "",
          "loss": "",
          "pct_loss": "",
          "overlap": "",
          "ket": "",
          "status": "Plan",
          "eff": ""
        },
        {
          "key": "20260723-MS-DT 4-PLAN",
          "date": "7/23/2026",
          "shift": "MS",
          "cluster": "CM6",
          "group": "TBR DT",
          "mc": "DT 4",
          "jenis": "D",
          "plan": "11:05",
          "doff": "",
          "start": "",
          "code": "",
          "std": "13.5",
          "dt_mc": "",
          "dt_proc": "",
          "loss": "",
          "pct_loss": "",
          "overlap": "",
          "ket": "",
          "status": "Plan",
          "eff": ""
        },
        {
          "key": "20260723-MS-L 9-PLAN",
          "date": "7/23/2026",
          "shift": "MS",
          "cluster": "CM6",
          "group": "TBR L",
          "mc": "L 9",
          "jenis": "GF",
          "plan": "06:00",
          "doff": "06:00",
          "start": "08:55",
          "code": "",
          "std": "35.8",
          "dt_mc": "175",
          "dt_proc": "175",
          "loss": "-139.2",
          "pct_loss": "-29.0%",
          "overlap": "420",
          "ket": "D+Gp 455/3 changsu +GT test ok 08:30 gf +C",
          "status": "Actual",
          "eff": "-389.0%"
        },
        {
          "key": "20260723-MS-L 3-PLAN",
          "date": "7/23/2026",
          "shift": "MS",
          "cluster": "CM6",
          "group": "TBR L",
          "mc": "L 3",
          "jenis": "GF",
          "plan": "09:00",
          "doff": "08:15",
          "start": "09:30",
          "code": "",
          "std": "35.8",
          "dt_mc": "",
          "dt_proc": "",
          "loss": "",
          "pct_loss": "",
          "overlap": "195",
          "ket": "D+GF+C+Dah L9",
          "status": "Actual",
          "eff": ""
        },
        {
          "key": "20260723-MS-L 11-PLAN",
          "date": "7/23/2026",
          "shift": "MS",
          "cluster": "CM6",
          "group": "TBR L",
          "mc": "L 11",
          "jenis": "GF",
          "plan": "11:00",
          "doff": "10:30",
          "start": "12:15",
          "code": "",
          "std": "35.8",
          "dt_mc": "",
          "dt_proc": "",
          "loss": "",
          "pct_loss": "",
          "overlap": "",
          "ket": "Tunggu intruksi +D+GF+C ok",
          "status": "Actual",
          "eff": ""
        },
        {
          "key": "20260723-MS-L 14-PLAN",
          "date": "7/23/2026",
          "shift": "MS",
          "cluster": "CM6",
          "group": "TBR L",
          "mc": "L 14",
          "jenis": "GF",
          "plan": "07:00",
          "doff": "08:00",
          "start": "12:25",
          "code": "",
          "std": "35.8",
          "dt_mc": "",
          "dt_proc": "",
          "loss": "",
          "pct_loss": "",
          "overlap": "360",
          "ket": "D+GF+C+TF+Cleaning mc",
          "status": "Actual",
          "eff": ""
        },
        {
          "key": "20260723-MS-L 7-PLAN",
          "date": "7/23/2026",
          "shift": "MS",
          "cluster": "CM6",
          "group": "TBR L",
          "mc": "L 7",
          "jenis": "GF",
          "plan": "12:00",
          "doff": "12:00",
          "start": "13:00",
          "code": "",
          "std": "35.8",
          "dt_mc": "",
          "dt_proc": "",
          "loss": "",
          "pct_loss": "",
          "overlap": "",
          "ket": "D+GF+C+Dah L11 dan L14",
          "status": "Actual",
          "eff": ""
        },
        {
          "key": "20260723-MS-L 13-PLAN",
          "date": "7/23/2026",
          "shift": "MS",
          "cluster": "CM6",
          "group": "TBR L",
          "mc": "L 13",
          "jenis": "GF",
          "plan": "10:30",
          "doff": "10:15",
          "start": "14:00",
          "code": "L",
          "std": "35.8",
          "dt_mc": "225",
          "dt_proc": "",
          "loss": "",
          "pct_loss": "",
          "overlap": "120",
          "ket": "D+TF",
          "status": "Actual",
          "eff": ""
        },
        {
          "key": "20260723-MS-L 10-PLAN",
          "date": "7/23/2026",
          "shift": "MS",
          "cluster": "CM6",
          "group": "TBR L",
          "mc": "L 10",
          "jenis": "GF",
          "plan": "07:30",
          "doff": "",
          "start": "",
          "code": "",
          "std": "35.8",
          "dt_mc": "",
          "dt_proc": "",
          "loss": "",
          "pct_loss": "",
          "overlap": "",
          "ket": "",
          "status": "Plan",
          "eff": ""
        }
      ]
    },
    "AS": {
      "cm3": [
        {
          "key": "20260723-AS-HE 2-PLAN",
          "date": "7/23/2026",
          "shift": "",
          "cluster": "CM3",
          "group": "Alidra Heli",
          "mc": "HE 2",
          "jenis": "D",
          "plan": "20:50",
          "doff": "",
          "start": "",
          "code": "",
          "std": "17.8",
          "dt_mc": "",
          "dt_proc": "",
          "loss": "",
          "pct_loss": "",
          "overlap": "",
          "ket": "",
          "status": "Plan",
          "eff": ""
        },
        {
          "key": "20260723-AS-DT 13-PLAN",
          "date": "7/23/2026",
          "shift": "",
          "cluster": "CM3",
          "group": "DT New",
          "mc": "DT 13",
          "jenis": "D",
          "plan": "15:40",
          "doff": "",
          "start": "",
          "code": "",
          "std": "13.5",
          "dt_mc": "",
          "dt_proc": "",
          "loss": "",
          "pct_loss": "",
          "overlap": "",
          "ket": "D 1",
          "status": "Plan",
          "eff": ""
        },
        {
          "key": "20260723-AS-DT 10-PLAN",
          "date": "7/23/2026",
          "shift": "",
          "cluster": "CM3",
          "group": "DT New",
          "mc": "DT 10",
          "jenis": "D",
          "plan": "16:15",
          "doff": "",
          "start": "",
          "code": "",
          "std": "13.5",
          "dt_mc": "",
          "dt_proc": "",
          "loss": "",
          "pct_loss": "",
          "overlap": "",
          "ket": "D 2",
          "status": "Plan",
          "eff": ""
        },
        {
          "key": "20260723-AS-DT 14-PLAN",
          "date": "7/23/2026",
          "shift": "",
          "cluster": "CM3",
          "group": "DT New",
          "mc": "DT 14",
          "jenis": "GF",
          "plan": "16:20",
          "doff": "",
          "start": "",
          "code": "",
          "std": "82.7",
          "dt_mc": "",
          "dt_proc": "",
          "loss": "",
          "pct_loss": "",
          "overlap": "",
          "ket": "GF",
          "status": "Plan",
          "eff": ""
        },
        {
          "key": "20260723-AS-DT 8-PLAN",
          "date": "7/23/2026",
          "shift": "",
          "cluster": "CM3",
          "group": "DT New",
          "mc": "DT 8",
          "jenis": "D",
          "plan": "18:35",
          "doff": "",
          "start": "",
          "code": "",
          "std": "13.5",
          "dt_mc": "",
          "dt_proc": "",
          "loss": "",
          "pct_loss": "",
          "overlap": "",
          "ket": "D 1",
          "status": "Plan",
          "eff": ""
        },
        {
          "key": "20260723-AS-DT 12-PLAN",
          "date": "7/23/2026",
          "shift": "",
          "cluster": "CM3",
          "group": "DT New",
          "mc": "DT 12",
          "jenis": "D",
          "plan": "19:05",
          "doff": "",
          "start": "",
          "code": "",
          "std": "13.5",
          "dt_mc": "",
          "dt_proc": "",
          "loss": "",
          "pct_loss": "",
          "overlap": "",
          "ket": "D 2",
          "status": "Plan",
          "eff": ""
        },
        {
          "key": "20260723-AS-DT 9-PLAN",
          "date": "7/23/2026",
          "shift": "",
          "cluster": "CM3",
          "group": "DT New",
          "mc": "DT 9",
          "jenis": "D",
          "plan": "19:55",
          "doff": "",
          "start": "",
          "code": "",
          "std": "13.5",
          "dt_mc": "",
          "dt_proc": "",
          "loss": "",
          "pct_loss": "",
          "overlap": "",
          "ket": "D 2 + GF 1/4",
          "status": "Plan",
          "eff": ""
        },
        {
          "key": "20260723-AS-DL-PLAN",
          "date": "7/23/2026",
          "shift": "",
          "cluster": "CM3",
          "group": "NL",
          "mc": "DL",
          "jenis": "GF",
          "plan": "15:10",
          "doff": "",
          "start": "",
          "code": "",
          "std": "37.1",
          "dt_mc": "",
          "dt_proc": "",
          "loss": "",
          "pct_loss": "",
          "overlap": "",
          "ket": "",
          "status": "Plan",
          "eff": ""
        },
        {
          "key": "20260723-AS-L 15-PLAN",
          "date": "7/23/2026",
          "shift": "",
          "cluster": "CM3",
          "group": "NL",
          "mc": "L 15",
          "jenis": "GF",
          "plan": "18:30",
          "doff": "",
          "start": "",
          "code": "",
          "std": "35.8",
          "dt_mc": "",
          "dt_proc": "",
          "loss": "",
          "pct_loss": "",
          "overlap": "",
          "ket": "",
          "status": "Plan",
          "eff": ""
        }
      ],
      "cm6": []
    },
    "NS": {
      "cm3": [
        {
          "key": "20260723-NS-HE 5-PLAN",
          "date": "7/23/2026",
          "shift": "",
          "cluster": "CM3",
          "group": "Alidra Heli",
          "mc": "HE 5",
          "jenis": "GF",
          "plan": "22:10",
          "doff": "22:10",
          "start": "00:00",
          "code": "",
          "std": "97.3",
          "dt_mc": "110",
          "dt_proc": "110",
          "loss": "-12.7",
          "pct_loss": "-2.6%",
          "overlap": "460",
          "ket": "D+GF+patrol awal+Briefing+C",
          "status": "Actual",
          "eff": "-13.0%"
        },
        {
          "key": "20260723-NS-HE 7-PLAN",
          "date": "7/23/2026",
          "shift": "",
          "cluster": "CM3",
          "group": "Alidra Heli",
          "mc": "HE 7",
          "jenis": "GF",
          "plan": "01:15",
          "doff": "01:15",
          "start": "04:05",
          "code": "",
          "std": "97.3",
          "dt_mc": "170",
          "dt_proc": "170",
          "loss": "-72.7",
          "pct_loss": "-15.1%",
          "overlap": "",
          "ket": "D+GF+C+pergantian istirahat+ perbaikan LMF",
          "status": "Actual",
          "eff": "-74.7%"
        },
        {
          "key": "20260723-NS-HE 4-PLAN",
          "date": "7/23/2026",
          "shift": "",
          "cluster": "CM3",
          "group": "Alidra Heli",
          "mc": "HE 4",
          "jenis": "GF",
          "plan": "02:15",
          "doff": "02:15",
          "start": "05:50",
          "code": "",
          "std": "97.3",
          "dt_mc": "215",
          "dt_proc": "105",
          "loss": "-7.7",
          "pct_loss": "-1.6%",
          "overlap": "225",
          "ket": "D+GF+Dahulukan heli 7",
          "status": "Actual",
          "eff": "-7.9%"
        },
        {
          "key": "20260723-NS-HE 2-PLAN",
          "date": "7/23/2026",
          "shift": "",
          "cluster": "CM3",
          "group": "Alidra Heli",
          "mc": "HE 2",
          "jenis": "GF",
          "plan": "03:30",
          "doff": "03:30",
          "start": "06:00",
          "code": "L",
          "std": "97.3",
          "dt_mc": "150",
          "dt_proc": "",
          "loss": "",
          "pct_loss": "",
          "overlap": "",
          "ket": "sudah doff+dahulukan heli 7,4",
          "status": "Actual",
          "eff": ""
        },
        {
          "key": "20260723-NS-DT 14-PLAN",
          "date": "7/23/2026",
          "shift": "",
          "cluster": "CM3",
          "group": "DT New",
          "mc": "DT 14",
          "jenis": "D",
          "plan": "23:50",
          "doff": "23:50",
          "start": "00:05",
          "code": "",
          "std": "13.5",
          "dt_mc": "15",
          "dt_proc": "15",
          "loss": "-1.5",
          "pct_loss": "-0.3%",
          "overlap": "25",
          "ket": "D+C+HB",
          "status": "Actual",
          "eff": "-11.5%"
        },
        {
          "key": "20260723-NS-DT 14-PLAN",
          "date": "7/23/2026",
          "shift": "",
          "cluster": "CM3",
          "group": "DT New",
          "mc": "DT 14",
          "jenis": "D",
          "plan": "23:50",
          "doff": "23:50",
          "start": "00:05",
          "code": "",
          "std": "13.5",
          "dt_mc": "15",
          "dt_proc": "15",
          "loss": "-1.5",
          "pct_loss": "-0.3%",
          "overlap": "25",
          "ket": "",
          "status": "Plan",
          "eff": "-11.5%"
        },
        {
          "key": "20260723-NS-DT 13-PLAN",
          "date": "7/23/2026",
          "shift": "",
          "cluster": "CM3",
          "group": "DT New",
          "mc": "DT 13",
          "jenis": "D",
          "plan": "",
          "doff": "00:00",
          "start": "00:15",
          "code": "",
          "std": "13.5",
          "dt_mc": "15",
          "dt_proc": "10",
          "loss": "3.5",
          "pct_loss": "0.7%",
          "overlap": "220",
          "ket": "D+C+HB",
          "status": "Actual",
          "eff": "25.7%"
        },
        {
          "key": "20260723-NS-DT 13-PLAN",
          "date": "7/23/2026",
          "shift": "",
          "cluster": "CM3",
          "group": "DT New",
          "mc": "DT 13",
          "jenis": "D",
          "plan": "",
          "doff": "",
          "start": "00:15",
          "code": "",
          "std": "13.5",
          "dt_mc": "15",
          "dt_proc": "10",
          "loss": "3.5",
          "pct_loss": "0.7%",
          "overlap": "220",
          "ket": "D + C + HB",
          "status": "Plan",
          "eff": "25.7%"
        },
        {
          "key": "20260723-NS-DT 10-PLAN",
          "date": "7/23/2026",
          "shift": "",
          "cluster": "CM3",
          "group": "DT New",
          "mc": "DT 10",
          "jenis": "GF",
          "plan": "23:55",
          "doff": "23:55",
          "start": "01:10",
          "code": "",
          "std": "82.7",
          "dt_mc": "",
          "dt_proc": "",
          "loss": "",
          "pct_loss": "",
          "overlap": "295",
          "ket": "D+GF",
          "status": "Actual",
          "eff": ""
        },
        {
          "key": "20260723-NS-DT 10-PLAN",
          "date": "7/23/2026",
          "shift": "",
          "cluster": "CM3",
          "group": "DT New",
          "mc": "DT 10",
          "jenis": "GF",
          "plan": "23:55",
          "doff": "23:55",
          "start": "01:10",
          "code": "",
          "std": "82.7",
          "dt_mc": "",
          "dt_proc": "",
          "loss": "",
          "pct_loss": "",
          "overlap": "295",
          "ket": "D+ GF",
          "status": "Plan",
          "eff": ""
        },
        {
          "key": "20260723-NS-DT 8-PLAN",
          "date": "7/23/2026",
          "shift": "",
          "cluster": "CM3",
          "group": "DT New",
          "mc": "DT 8",
          "jenis": "D",
          "plan": "02:10",
          "doff": "02:10",
          "start": "02:25",
          "code": "",
          "std": "13.5",
          "dt_mc": "15",
          "dt_proc": "15",
          "loss": "-1.5",
          "pct_loss": "-0.3%",
          "overlap": "",
          "ket": "D+C+HB",
          "status": "Actual",
          "eff": "-11.5%"
        },
        {
          "key": "20260723-NS-DT 8-PLAN",
          "date": "7/23/2026",
          "shift": "",
          "cluster": "CM3",
          "group": "DT New",
          "mc": "DT 8",
          "jenis": "D",
          "plan": "02:10",
          "doff": "02:10",
          "start": "02:25",
          "code": "",
          "std": "13.5",
          "dt_mc": "15",
          "dt_proc": "15",
          "loss": "-1.5",
          "pct_loss": "-0.3%",
          "overlap": "115",
          "ket": "D + C + HB",
          "status": "Plan",
          "eff": "-11.5%"
        },
        {
          "key": "20260723-NS-DT 12-PLAN",
          "date": "7/23/2026",
          "shift": "",
          "cluster": "CM3",
          "group": "DT New",
          "mc": "DT 12",
          "jenis": "GF",
          "plan": "02:30",
          "doff": "02:30",
          "start": "03:40",
          "code": "",
          "std": "82.7",
          "dt_mc": "70",
          "dt_proc": "70",
          "loss": "12.7",
          "pct_loss": "2.7%",
          "overlap": "",
          "ket": "D+GF",
          "status": "Actual",
          "eff": "15.4%"
        },
        {
          "key": "20260723-NS-DT 12-PLAN",
          "date": "7/23/2026",
          "shift": "",
          "cluster": "CM3",
          "group": "DT New",
          "mc": "DT 12",
          "jenis": "GF",
          "plan": "02:30",
          "doff": "02:30",
          "start": "03:40",
          "code": "",
          "std": "82.7",
          "dt_mc": "70",
          "dt_proc": "70",
          "loss": "12.7",
          "pct_loss": "2.7%",
          "overlap": "",
          "ket": "D + C + HB",
          "status": "Plan",
          "eff": "15.4%"
        },
        {
          "key": "20260723-NS-DT 9-PLAN",
          "date": "7/23/2026",
          "shift": "",
          "cluster": "CM3",
          "group": "DT New",
          "mc": "DT 9",
          "jenis": "GF",
          "plan": "03:00",
          "doff": "03:00",
          "start": "04:50",
          "code": "",
          "std": "82.7",
          "dt_mc": "110",
          "dt_proc": "70",
          "loss": "12.7",
          "pct_loss": "2.7%",
          "overlap": "",
          "ket": "D+GF 3/4 + dahulukan dt 12",
          "status": "Actual",
          "eff": "15.4%"
        },
        {
          "key": "20260723-NS-DT 9-PLAN",
          "date": "7/23/2026",
          "shift": "",
          "cluster": "CM3",
          "group": "DT New",
          "mc": "DT 9",
          "jenis": "GF",
          "plan": "03:00",
          "doff": "03:00",
          "start": "04:50",
          "code": "",
          "std": "82.72727273",
          "dt_mc": "110",
          "dt_proc": "70",
          "loss": "12.7",
          "pct_loss": "2.7%",
          "overlap": "",
          "ket": "D + C + HB + GF 3/4 dah 12",
          "status": "Plan",
          "eff": "15.4%"
        },
        {
          "key": "20260723-NS-DT 11-PLAN",
          "date": "7/23/2026",
          "shift": "",
          "cluster": "CM3",
          "group": "DT New",
          "mc": "DT 11",
          "jenis": "GF",
          "plan": "22:00",
          "doff": "",
          "start": "",
          "code": "",
          "std": "82.72727273",
          "dt_mc": "",
          "dt_proc": "",
          "loss": "",
          "pct_loss": "",
          "overlap": "",
          "ket": "MC Stop",
          "status": "Plan",
          "eff": ""
        },
        {
          "key": "20260723-NS-L 15-PLAN",
          "date": "7/23/2026",
          "shift": "",
          "cluster": "CM3",
          "group": "NL",
          "mc": "L 15",
          "jenis": "GF",
          "plan": "01:00",
          "doff": "23:30",
          "start": "01:00",
          "code": "",
          "std": "35.78571429",
          "dt_mc": "90",
          "dt_proc": "90",
          "loss": "-54.2",
          "pct_loss": "-11.3%",
          "overlap": "35",
          "ket": "D+ GF + Tunggu Feeding",
          "status": "Actual",
          "eff": "-151.5%"
        },
        {
          "key": "20260723-NS-L 18-PLAN",
          "date": "7/23/2026",
          "shift": "",
          "cluster": "CM3",
          "group": "NL",
          "mc": "L 18",
          "jenis": "GF",
          "plan": "04:00",
          "doff": "03:00",
          "start": "04:00",
          "code": "",
          "std": "35.78571429",
          "dt_mc": "60",
          "dt_proc": "60",
          "loss": "-24.2",
          "pct_loss": "-5.0%",
          "overlap": "",
          "ket": "D+ GF + Tunggu Feeding",
          "status": "Actual",
          "eff": "-67.7%"
        }
      ],
      "cm6": [
        {
          "key": "20260723-NS-Delta 1-PLAN",
          "date": "7/23/2026",
          "shift": "NS",
          "cluster": "CM6",
          "group": "TBR Delta",
          "mc": "Delta 1",
          "jenis": "GF",
          "plan": "22:50",
          "doff": "22:50",
          "start": "00:00",
          "code": "",
          "std": "37.1",
          "dt_mc": "70",
          "dt_proc": "70",
          "loss": "-33.0",
          "pct_loss": "-6.9%",
          "overlap": "230",
          "ket": "Doff + gf + R",
          "status": "Actual",
          "eff": "-88.9%"
        },
        {
          "key": "20260723-NS-Delta 10-PLAN",
          "date": "7/23/2026",
          "shift": "NS",
          "cluster": "CM6",
          "group": "TBR Delta",
          "mc": "Delta 10",
          "jenis": "GF",
          "plan": "05:00",
          "doff": "04:45",
          "start": "05:20",
          "code": "",
          "std": "37.1",
          "dt_mc": "35",
          "dt_proc": "35",
          "loss": "2.1",
          "pct_loss": "0.4%",
          "overlap": "",
          "ket": "Doff + gf + R",
          "status": "Actual",
          "eff": "5.5%"
        },
        {
          "key": "20260723-NS-DT 4-PLAN",
          "date": "7/23/2026",
          "shift": "NS",
          "cluster": "CM6",
          "group": "TBR DT",
          "mc": "DT 4",
          "jenis": "GF",
          "plan": "22:00",
          "doff": "22:00",
          "start": "00:25",
          "code": "",
          "std": "82.7",
          "dt_mc": "145",
          "dt_proc": "145",
          "loss": "-62.3",
          "pct_loss": "-13.0%",
          "overlap": "160",
          "ket": "D+GF+BRIEFING+PAT AWAL+G .TENSIONER",
          "status": "Actual",
          "eff": "-75.3%"
        },
        {
          "key": "20260723-NS-DT 3-PLAN",
          "date": "7/23/2026",
          "shift": "NS",
          "cluster": "CM6",
          "group": "TBR DT",
          "mc": "DT 3",
          "jenis": "D",
          "plan": "22:00",
          "doff": "22:00",
          "start": "00:40",
          "code": "REP",
          "std": "13.5",
          "dt_mc": "160",
          "dt_proc": "",
          "loss": "",
          "pct_loss": "",
          "overlap": "320",
          "ket": "",
          "status": "Actual",
          "eff": ""
        },
        {
          "key": "20260723-NS-DT 6-PLAN",
          "date": "7/23/2026",
          "shift": "NS",
          "cluster": "CM6",
          "group": "TBR DT",
          "mc": "DT 6",
          "jenis": "D",
          "plan": "01:50",
          "doff": "01:50",
          "start": "02:40",
          "code": "",
          "std": "13.5",
          "dt_mc": "50",
          "dt_proc": "50",
          "loss": "-36.5",
          "pct_loss": "-7.6%",
          "overlap": "",
          "ket": "D+C+HB (10) + PERG ISTIRAHAT",
          "status": "Actual",
          "eff": "-271.6%"
        },
        {
          "key": "20260723-NS-DT 1-PLAN",
          "date": "7/23/2026",
          "shift": "NS",
          "cluster": "CM6",
          "group": "TBR DT",
          "mc": "DT 1",
          "jenis": "D",
          "plan": "02:50",
          "doff": "02:50",
          "start": "03:20",
          "code": "",
          "std": "13.5",
          "dt_mc": "30",
          "dt_proc": "30",
          "loss": "-16.5",
          "pct_loss": "-3.4%",
          "overlap": "190",
          "ket": "D+C+HB(12)",
          "status": "Actual",
          "eff": "-123.0%"
        },
        {
          "key": "20260723-NS-L 1-PLAN",
          "date": "7/23/2026",
          "shift": "NS",
          "cluster": "CM6",
          "group": "TBR L",
          "mc": "L 1",
          "jenis": "GF",
          "plan": "23:40",
          "doff": "22:50",
          "start": "23:30",
          "code": "",
          "std": "35.8",
          "dt_mc": "40",
          "dt_proc": "40",
          "loss": "-4.2",
          "pct_loss": "-0.9%",
          "overlap": "",
          "ket": "GF",
          "status": "Actual",
          "eff": "-11.8%"
        },
        {
          "key": "20260723-NS-L 7-PLAN",
          "date": "7/23/2026",
          "shift": "NS",
          "cluster": "CM6",
          "group": "TBR L",
          "mc": "L 7",
          "jenis": "GF",
          "plan": "04:00",
          "doff": "02:50",
          "start": "03:30",
          "code": "",
          "std": "35.8",
          "dt_mc": "40",
          "dt_proc": "40",
          "loss": "-4.2",
          "pct_loss": "-0.9%",
          "overlap": "55",
          "ket": "D+gf",
          "status": "Actual",
          "eff": "-11.8%"
        },
        {
          "key": "20260723-NS-L 5-PLAN",
          "date": "7/23/2026",
          "shift": "NS",
          "cluster": "CM6",
          "group": "TBR L",
          "mc": "L 5",
          "jenis": "GF",
          "plan": "22:15",
          "doff": "22:15",
          "start": "03:45",
          "code": "",
          "std": "35.8",
          "dt_mc": "330",
          "dt_proc": "15",
          "loss": "20.8",
          "pct_loss": "4.3%",
          "overlap": "445",
          "ket": "D +hp ke 275/3 + test QA ok 03:15",
          "status": "Actual",
          "eff": "58.1%"
        },
        {
          "key": "20260723-NS-L 2-PLAN",
          "date": "7/23/2026",
          "shift": "NS",
          "cluster": "CM6",
          "group": "TBR L",
          "mc": "L 2",
          "jenis": "GF",
          "plan": "04:00",
          "doff": "03:50",
          "start": "04:10",
          "code": "",
          "std": "35.8",
          "dt_mc": "20",
          "dt_proc": "20",
          "loss": "15.8",
          "pct_loss": "3.3%",
          "overlap": "90",
          "ket": "D+gf",
          "status": "Actual",
          "eff": "44.1%"
        },
        {
          "key": "20260723-NS-L 4-PLAN",
          "date": "7/23/2026",
          "shift": "NS",
          "cluster": "CM6",
          "group": "TBR L",
          "mc": "L 4",
          "jenis": "GF",
          "plan": "02:40",
          "doff": "02:40",
          "start": "05:40",
          "code": "",
          "std": "35.8",
          "dt_mc": "180",
          "dt_proc": "90",
          "loss": "-54.2",
          "pct_loss": "-11.3%",
          "overlap": "",
          "ket": "D+ hp ke 275/3 changsu Test QA ok jam 05:00",
          "status": "Actual",
          "eff": "-151.5%"
        },
        {
          "key": "20260723-NS-L 9-PLAN",
          "date": "7/23/2026",
          "shift": "NS",
          "cluster": "CM6",
          "group": "TBR L",
          "mc": "L 9",
          "jenis": "GF",
          "plan": "05:45",
          "doff": "05:45",
          "start": "06:00",
          "code": "L",
          "std": "35.8",
          "dt_mc": "15",
          "dt_proc": "",
          "loss": "",
          "pct_loss": "",
          "overlap": "",
          "ket": "",
          "status": "Plan",
          "eff": ""
        }
      ]
    }
  },
  "rows": [
    {
      "key": "20260723-MS-HE 2-PLAN",
      "date": "7/23/2026",
      "shift": "",
      "cluster": "CM3",
      "group": "Alidra Heli",
      "mc": "HE 2",
      "jenis": "GF",
      "plan": "06:00",
      "doff": "06:00",
      "start": "07:15",
      "code": "",
      "std": "97.3",
      "dt_mc": "75",
      "dt_proc": "75",
      "loss": "22.3",
      "pct_loss": "4.7%",
      "overlap": "360",
      "ket": "GF. Awal (No 86-96 1x doff) + C + Jalan ½ Length",
      "status": "Actual",
      "eff": "22.9%"
    },
    {
      "key": "20260723-MS-HE 1-PLAN",
      "date": "7/23/2026",
      "shift": "",
      "cluster": "CM3",
      "group": "Alidra Heli",
      "mc": "HE 1",
      "jenis": "GF",
      "plan": "10:15",
      "doff": "10:15",
      "start": "12:00",
      "code": "",
      "std": "97.3",
      "dt_mc": "105",
      "dt_proc": "105",
      "loss": "-7.7",
      "pct_loss": "-1.6%",
      "overlap": "830",
      "ket": "D + GF ½ MC (1x doff) + C + P. Istirahat + Briefing",
      "status": "Actual",
      "eff": "-7.9%"
    },
    {
      "key": "20260723-MS-HE 8-PLAN",
      "date": "7/23/2026",
      "shift": "",
      "cluster": "CM3",
      "group": "Alidra Heli",
      "mc": "HE 8",
      "jenis": "D",
      "plan": "12:30",
      "doff": "12:30",
      "start": "13:15",
      "code": "",
      "std": "17.8",
      "dt_mc": "45",
      "dt_proc": "45",
      "loss": "-27.2",
      "pct_loss": "-5.7%",
      "overlap": "90",
      "ket": "D + C + HB (68 spdl)",
      "status": "Actual",
      "eff": "-153.1%"
    },
    {
      "key": "20260723-MS-HE 6-PLAN",
      "date": "7/23/2026",
      "shift": "",
      "cluster": "CM3",
      "group": "Alidra Heli",
      "mc": "HE 6",
      "jenis": "GF",
      "plan": "13:30",
      "doff": "13:30",
      "start": "14:00",
      "code": "L",
      "std": "97.3",
      "dt_mc": "30",
      "dt_proc": "",
      "loss": "",
      "pct_loss": "",
      "overlap": "",
      "ket": "D. Akhir (Belum Doff)",
      "status": "Actual",
      "eff": ""
    },
    {
      "key": "20260723-MS-DT 12-PLAN",
      "date": "7/23/2026",
      "shift": "",
      "cluster": "CM3",
      "group": "DT New",
      "mc": "DT 12",
      "jenis": "D",
      "plan": "11:10",
      "doff": "11:10",
      "start": "11:35",
      "code": "",
      "std": "13.5",
      "dt_mc": "25",
      "dt_proc": "25",
      "loss": "-11.5",
      "pct_loss": "-2.4%",
      "overlap": "",
      "ket": "Doff + C + Hb + briefing",
      "status": "Actual",
      "eff": "-85.8%"
    },
    {
      "key": "20260723-MS-L 16-PLAN",
      "date": "7/23/2026",
      "shift": "",
      "cluster": "CM3",
      "group": "NL",
      "mc": "L 16",
      "jenis": "GF",
      "plan": "11:30",
      "doff": "11:30",
      "start": "12:00",
      "code": "",
      "std": "35.8",
      "dt_mc": "30",
      "dt_proc": "30",
      "loss": "5.8",
      "pct_loss": "1.2%",
      "overlap": "",
      "ket": "D + GF + C",
      "status": "Actual",
      "eff": "16.2%"
    },
    {
      "key": "20260723-MS-Delta 11-PLAN",
      "date": "7/23/2026",
      "shift": "MS",
      "cluster": "CM6",
      "group": "TBR Delta",
      "mc": "Delta 11",
      "jenis": "GF",
      "plan": "08:00",
      "doff": "08:10",
      "start": "09:00",
      "code": "",
      "std": "37.1",
      "dt_mc": "50",
      "dt_proc": "50",
      "loss": "-13.0",
      "pct_loss": "-2.7%",
      "overlap": "350",
      "ket": "Doff + Gf + R",
      "status": "Actual",
      "eff": "-35.0%"
    },
    {
      "key": "20260723-MS-Delta 5-PLAN",
      "date": "7/23/2026",
      "shift": "MS",
      "cluster": "CM6",
      "group": "TBR Delta",
      "mc": "Delta 5",
      "jenis": "GF",
      "plan": "08:30",
      "doff": "08:25",
      "start": "10:35",
      "code": "",
      "std": "112.8",
      "dt_mc": "130",
      "dt_proc": "95",
      "loss": "17.8",
      "pct_loss": "3.7%",
      "overlap": "305",
      "ket": "Doff + Gf (1xdoff) + dahulukan no.11 + p.istirahat + R",
      "status": "Actual",
      "eff": "15.8%"
    },
    {
      "key": "20260723-MS-Delta 13-PLAN",
      "date": "7/23/2026",
      "shift": "MS",
      "cluster": "CM6",
      "group": "TBR Delta",
      "mc": "Delta 13",
      "jenis": "GF",
      "plan": "10:00",
      "doff": "09:35",
      "start": "11:30",
      "code": "",
      "std": "37.1",
      "dt_mc": "115",
      "dt_proc": "55",
      "loss": "-18.0",
      "pct_loss": "-3.7%",
      "overlap": "",
      "ket": "Doff + Gf + Dahulukan no.5 + cleaning m/c + R",
      "status": "Actual",
      "eff": "-48.4%"
    },
    {
      "key": "20260723-MS-Delta 4-PLAN",
      "date": "7/23/2026",
      "shift": "MS",
      "cluster": "CM6",
      "group": "TBR Delta",
      "mc": "Delta 4",
      "jenis": "GF",
      "plan": "10:30",
      "doff": "10:30",
      "start": "13:30",
      "code": "",
      "std": "112.8",
      "dt_mc": "180",
      "dt_proc": "120",
      "loss": "-7.2",
      "pct_loss": "-1.5%",
      "overlap": "",
      "ket": "Doff + Gf + Dahulukan no.13 + G.tensioner LMN + R",
      "status": "Actual",
      "eff": "-6.4%"
    },
    {
      "key": "20260723-MS-Delta 10-PLAN",
      "date": "7/23/2026",
      "shift": "MS",
      "cluster": "CM6",
      "group": "TBR Delta",
      "mc": "Delta 10",
      "jenis": "GF",
      "plan": "13:30",
      "doff": "13:15",
      "start": "14:00",
      "code": "L",
      "std": "37.1",
      "dt_mc": "45",
      "dt_proc": "",
      "loss": "",
      "pct_loss": "",
      "overlap": "",
      "ket": "Doff + Gf + Tf(rewending)",
      "status": "Actual",
      "eff": ""
    },
    {
      "key": "20260723-MS-DT 5-PLAN",
      "date": "7/23/2026",
      "shift": "MS",
      "cluster": "CM6",
      "group": "TBR DT",
      "mc": "DT 5",
      "jenis": "D",
      "plan": "06:05",
      "doff": "06:05",
      "start": "06:30",
      "code": "",
      "std": "13.5",
      "dt_mc": "25",
      "dt_proc": "25",
      "loss": "-11.5",
      "pct_loss": "-2.4%",
      "overlap": "",
      "ket": "Doff Criling hb 18 patroling awal",
      "status": "Actual",
      "eff": "-85.8%"
    },
    {
      "key": "20260723-MS-DT 7-PLAN",
      "date": "7/23/2026",
      "shift": "MS",
      "cluster": "CM6",
      "group": "TBR DT",
      "mc": "DT 7",
      "jenis": "D",
      "plan": "07:30",
      "doff": "07:25",
      "start": "07:35",
      "code": "",
      "std": "13.5",
      "dt_mc": "10",
      "dt_proc": "10",
      "loss": "3.5",
      "pct_loss": "0.7%",
      "overlap": "395",
      "ket": "Doff Criling hb 13 Briefing",
      "status": "Actual",
      "eff": "25.7%"
    },
    {
      "key": "20260723-MS-DT 2-PLAN",
      "date": "7/23/2026",
      "shift": "MS",
      "cluster": "CM6",
      "group": "TBR DT",
      "mc": "DT 2",
      "jenis": "GF",
      "plan": "06:35",
      "doff": "06:35",
      "start": "08:25",
      "code": "",
      "std": "82.7",
      "dt_mc": "110",
      "dt_proc": "50",
      "loss": "32.7",
      "pct_loss": "6.8%",
      "overlap": "1295",
      "ket": "Doff Gf dah dt 7",
      "status": "Actual",
      "eff": "39.6%"
    },
    {
      "key": "20260723-MS-DT 3-PLAN",
      "date": "7/23/2026",
      "shift": "MS",
      "cluster": "CM6",
      "group": "TBR DT",
      "mc": "DT 3",
      "jenis": "GF",
      "plan": "11:20",
      "doff": "11:25",
      "start": "12:35",
      "code": "",
      "std": "82.7",
      "dt_mc": "70",
      "dt_proc": "70",
      "loss": "12.7",
      "pct_loss": "2.7%",
      "overlap": "",
      "ket": "Doff  Gf dah dt 4",
      "status": "Actual",
      "eff": "15.4%"
    },
    {
      "key": "20260723-MS-DT 6-PLAN",
      "date": "7/23/2026",
      "shift": "MS",
      "cluster": "CM6",
      "group": "TBR DT",
      "mc": "DT 6",
      "jenis": "GF",
      "plan": "13:25",
      "doff": "13:35",
      "start": "14:00",
      "code": "L",
      "std": "82.7",
      "dt_mc": "25",
      "dt_proc": "",
      "loss": "",
      "pct_loss": "",
      "overlap": "",
      "ket": "Doff Gf (2× feeding)",
      "status": "Actual",
      "eff": ""
    },
    {
      "key": "20260723-MS-DT 2-PLAN",
      "date": "7/23/2026",
      "shift": "MS",
      "cluster": "CM6",
      "group": "TBR DT",
      "mc": "DT 2",
      "jenis": "GF",
      "plan": "06:35",
      "doff": "",
      "start": "",
      "code": "",
      "std": "82.7",
      "dt_mc": "",
      "dt_proc": "",
      "loss": "",
      "pct_loss": "",
      "overlap": "",
      "ket": "",
      "status": "Plan",
      "eff": ""
    },
    {
      "key": "20260723-MS-DT 4-PLAN",
      "date": "7/23/2026",
      "shift": "MS",
      "cluster": "CM6",
      "group": "TBR DT",
      "mc": "DT 4",
      "jenis": "D",
      "plan": "11:05",
      "doff": "",
      "start": "",
      "code": "",
      "std": "13.5",
      "dt_mc": "",
      "dt_proc": "",
      "loss": "",
      "pct_loss": "",
      "overlap": "",
      "ket": "",
      "status": "Plan",
      "eff": ""
    },
    {
      "key": "20260723-MS-L 9-PLAN",
      "date": "7/23/2026",
      "shift": "MS",
      "cluster": "CM6",
      "group": "TBR L",
      "mc": "L 9",
      "jenis": "GF",
      "plan": "06:00",
      "doff": "06:00",
      "start": "08:55",
      "code": "",
      "std": "35.8",
      "dt_mc": "175",
      "dt_proc": "175",
      "loss": "-139.2",
      "pct_loss": "-29.0%",
      "overlap": "420",
      "ket": "D+Gp 455/3 changsu +GT test ok 08:30 gf +C",
      "status": "Actual",
      "eff": "-389.0%"
    },
    {
      "key": "20260723-MS-L 3-PLAN",
      "date": "7/23/2026",
      "shift": "MS",
      "cluster": "CM6",
      "group": "TBR L",
      "mc": "L 3",
      "jenis": "GF",
      "plan": "09:00",
      "doff": "08:15",
      "start": "09:30",
      "code": "",
      "std": "35.8",
      "dt_mc": "",
      "dt_proc": "",
      "loss": "",
      "pct_loss": "",
      "overlap": "195",
      "ket": "D+GF+C+Dah L9",
      "status": "Actual",
      "eff": ""
    },
    {
      "key": "20260723-MS-L 11-PLAN",
      "date": "7/23/2026",
      "shift": "MS",
      "cluster": "CM6",
      "group": "TBR L",
      "mc": "L 11",
      "jenis": "GF",
      "plan": "11:00",
      "doff": "10:30",
      "start": "12:15",
      "code": "",
      "std": "35.8",
      "dt_mc": "",
      "dt_proc": "",
      "loss": "",
      "pct_loss": "",
      "overlap": "",
      "ket": "Tunggu intruksi +D+GF+C ok",
      "status": "Actual",
      "eff": ""
    },
    {
      "key": "20260723-MS-L 14-PLAN",
      "date": "7/23/2026",
      "shift": "MS",
      "cluster": "CM6",
      "group": "TBR L",
      "mc": "L 14",
      "jenis": "GF",
      "plan": "07:00",
      "doff": "08:00",
      "start": "12:25",
      "code": "",
      "std": "35.8",
      "dt_mc": "",
      "dt_proc": "",
      "loss": "",
      "pct_loss": "",
      "overlap": "360",
      "ket": "D+GF+C+TF+Cleaning mc",
      "status": "Actual",
      "eff": ""
    },
    {
      "key": "20260723-MS-L 7-PLAN",
      "date": "7/23/2026",
      "shift": "MS",
      "cluster": "CM6",
      "group": "TBR L",
      "mc": "L 7",
      "jenis": "GF",
      "plan": "12:00",
      "doff": "12:00",
      "start": "13:00",
      "code": "",
      "std": "35.8",
      "dt_mc": "",
      "dt_proc": "",
      "loss": "",
      "pct_loss": "",
      "overlap": "",
      "ket": "D+GF+C+Dah L11 dan L14",
      "status": "Actual",
      "eff": ""
    },
    {
      "key": "20260723-MS-L 13-PLAN",
      "date": "7/23/2026",
      "shift": "MS",
      "cluster": "CM6",
      "group": "TBR L",
      "mc": "L 13",
      "jenis": "GF",
      "plan": "10:30",
      "doff": "10:15",
      "start": "14:00",
      "code": "L",
      "std": "35.8",
      "dt_mc": "225",
      "dt_proc": "",
      "loss": "",
      "pct_loss": "",
      "overlap": "120",
      "ket": "D+TF",
      "status": "Actual",
      "eff": ""
    },
    {
      "key": "20260723-MS-L 10-PLAN",
      "date": "7/23/2026",
      "shift": "MS",
      "cluster": "CM6",
      "group": "TBR L",
      "mc": "L 10",
      "jenis": "GF",
      "plan": "07:30",
      "doff": "",
      "start": "",
      "code": "",
      "std": "35.8",
      "dt_mc": "",
      "dt_proc": "",
      "loss": "",
      "pct_loss": "",
      "overlap": "",
      "ket": "",
      "status": "Plan",
      "eff": ""
    },
    {
      "key": "20260723-AS-HE 2-PLAN",
      "date": "7/23/2026",
      "shift": "",
      "cluster": "CM3",
      "group": "Alidra Heli",
      "mc": "HE 2",
      "jenis": "D",
      "plan": "20:50",
      "doff": "",
      "start": "",
      "code": "",
      "std": "17.8",
      "dt_mc": "",
      "dt_proc": "",
      "loss": "",
      "pct_loss": "",
      "overlap": "",
      "ket": "",
      "status": "Plan",
      "eff": ""
    },
    {
      "key": "20260723-AS-DT 13-PLAN",
      "date": "7/23/2026",
      "shift": "",
      "cluster": "CM3",
      "group": "DT New",
      "mc": "DT 13",
      "jenis": "D",
      "plan": "15:40",
      "doff": "",
      "start": "",
      "code": "",
      "std": "13.5",
      "dt_mc": "",
      "dt_proc": "",
      "loss": "",
      "pct_loss": "",
      "overlap": "",
      "ket": "D 1",
      "status": "Plan",
      "eff": ""
    },
    {
      "key": "20260723-AS-DT 10-PLAN",
      "date": "7/23/2026",
      "shift": "",
      "cluster": "CM3",
      "group": "DT New",
      "mc": "DT 10",
      "jenis": "D",
      "plan": "16:15",
      "doff": "",
      "start": "",
      "code": "",
      "std": "13.5",
      "dt_mc": "",
      "dt_proc": "",
      "loss": "",
      "pct_loss": "",
      "overlap": "",
      "ket": "D 2",
      "status": "Plan",
      "eff": ""
    },
    {
      "key": "20260723-AS-DT 14-PLAN",
      "date": "7/23/2026",
      "shift": "",
      "cluster": "CM3",
      "group": "DT New",
      "mc": "DT 14",
      "jenis": "GF",
      "plan": "16:20",
      "doff": "",
      "start": "",
      "code": "",
      "std": "82.7",
      "dt_mc": "",
      "dt_proc": "",
      "loss": "",
      "pct_loss": "",
      "overlap": "",
      "ket": "GF",
      "status": "Plan",
      "eff": ""
    },
    {
      "key": "20260723-AS-DT 8-PLAN",
      "date": "7/23/2026",
      "shift": "",
      "cluster": "CM3",
      "group": "DT New",
      "mc": "DT 8",
      "jenis": "D",
      "plan": "18:35",
      "doff": "",
      "start": "",
      "code": "",
      "std": "13.5",
      "dt_mc": "",
      "dt_proc": "",
      "loss": "",
      "pct_loss": "",
      "overlap": "",
      "ket": "D 1",
      "status": "Plan",
      "eff": ""
    },
    {
      "key": "20260723-AS-DT 12-PLAN",
      "date": "7/23/2026",
      "shift": "",
      "cluster": "CM3",
      "group": "DT New",
      "mc": "DT 12",
      "jenis": "D",
      "plan": "19:05",
      "doff": "",
      "start": "",
      "code": "",
      "std": "13.5",
      "dt_mc": "",
      "dt_proc": "",
      "loss": "",
      "pct_loss": "",
      "overlap": "",
      "ket": "D 2",
      "status": "Plan",
      "eff": ""
    },
    {
      "key": "20260723-AS-DT 9-PLAN",
      "date": "7/23/2026",
      "shift": "",
      "cluster": "CM3",
      "group": "DT New",
      "mc": "DT 9",
      "jenis": "D",
      "plan": "19:55",
      "doff": "",
      "start": "",
      "code": "",
      "std": "13.5",
      "dt_mc": "",
      "dt_proc": "",
      "loss": "",
      "pct_loss": "",
      "overlap": "",
      "ket": "D 2 + GF 1/4",
      "status": "Plan",
      "eff": ""
    },
    {
      "key": "20260723-AS-DL-PLAN",
      "date": "7/23/2026",
      "shift": "",
      "cluster": "CM3",
      "group": "NL",
      "mc": "DL",
      "jenis": "GF",
      "plan": "15:10",
      "doff": "",
      "start": "",
      "code": "",
      "std": "37.1",
      "dt_mc": "",
      "dt_proc": "",
      "loss": "",
      "pct_loss": "",
      "overlap": "",
      "ket": "",
      "status": "Plan",
      "eff": ""
    },
    {
      "key": "20260723-AS-L 15-PLAN",
      "date": "7/23/2026",
      "shift": "",
      "cluster": "CM3",
      "group": "NL",
      "mc": "L 15",
      "jenis": "GF",
      "plan": "18:30",
      "doff": "",
      "start": "",
      "code": "",
      "std": "35.8",
      "dt_mc": "",
      "dt_proc": "",
      "loss": "",
      "pct_loss": "",
      "overlap": "",
      "ket": "",
      "status": "Plan",
      "eff": ""
    },
    {
      "key": "20260723-NS-HE 5-PLAN",
      "date": "7/23/2026",
      "shift": "",
      "cluster": "CM3",
      "group": "Alidra Heli",
      "mc": "HE 5",
      "jenis": "GF",
      "plan": "22:10",
      "doff": "22:10",
      "start": "00:00",
      "code": "",
      "std": "97.3",
      "dt_mc": "110",
      "dt_proc": "110",
      "loss": "-12.7",
      "pct_loss": "-2.6%",
      "overlap": "460",
      "ket": "D+GF+patrol awal+Briefing+C",
      "status": "Actual",
      "eff": "-13.0%"
    },
    {
      "key": "20260723-NS-HE 7-PLAN",
      "date": "7/23/2026",
      "shift": "",
      "cluster": "CM3",
      "group": "Alidra Heli",
      "mc": "HE 7",
      "jenis": "GF",
      "plan": "01:15",
      "doff": "01:15",
      "start": "04:05",
      "code": "",
      "std": "97.3",
      "dt_mc": "170",
      "dt_proc": "170",
      "loss": "-72.7",
      "pct_loss": "-15.1%",
      "overlap": "",
      "ket": "D+GF+C+pergantian istirahat+ perbaikan LMF",
      "status": "Actual",
      "eff": "-74.7%"
    },
    {
      "key": "20260723-NS-HE 4-PLAN",
      "date": "7/23/2026",
      "shift": "",
      "cluster": "CM3",
      "group": "Alidra Heli",
      "mc": "HE 4",
      "jenis": "GF",
      "plan": "02:15",
      "doff": "02:15",
      "start": "05:50",
      "code": "",
      "std": "97.3",
      "dt_mc": "215",
      "dt_proc": "105",
      "loss": "-7.7",
      "pct_loss": "-1.6%",
      "overlap": "225",
      "ket": "D+GF+Dahulukan heli 7",
      "status": "Actual",
      "eff": "-7.9%"
    },
    {
      "key": "20260723-NS-HE 2-PLAN",
      "date": "7/23/2026",
      "shift": "",
      "cluster": "CM3",
      "group": "Alidra Heli",
      "mc": "HE 2",
      "jenis": "GF",
      "plan": "03:30",
      "doff": "03:30",
      "start": "06:00",
      "code": "L",
      "std": "97.3",
      "dt_mc": "150",
      "dt_proc": "",
      "loss": "",
      "pct_loss": "",
      "overlap": "",
      "ket": "sudah doff+dahulukan heli 7,4",
      "status": "Actual",
      "eff": ""
    },
    {
      "key": "20260723-NS-DT 14-PLAN",
      "date": "7/23/2026",
      "shift": "",
      "cluster": "CM3",
      "group": "DT New",
      "mc": "DT 14",
      "jenis": "D",
      "plan": "23:50",
      "doff": "23:50",
      "start": "00:05",
      "code": "",
      "std": "13.5",
      "dt_mc": "15",
      "dt_proc": "15",
      "loss": "-1.5",
      "pct_loss": "-0.3%",
      "overlap": "25",
      "ket": "D+C+HB",
      "status": "Actual",
      "eff": "-11.5%"
    },
    {
      "key": "20260723-NS-DT 14-PLAN",
      "date": "7/23/2026",
      "shift": "",
      "cluster": "CM3",
      "group": "DT New",
      "mc": "DT 14",
      "jenis": "D",
      "plan": "23:50",
      "doff": "23:50",
      "start": "00:05",
      "code": "",
      "std": "13.5",
      "dt_mc": "15",
      "dt_proc": "15",
      "loss": "-1.5",
      "pct_loss": "-0.3%",
      "overlap": "25",
      "ket": "",
      "status": "Plan",
      "eff": "-11.5%"
    },
    {
      "key": "20260723-NS-DT 13-PLAN",
      "date": "7/23/2026",
      "shift": "",
      "cluster": "CM3",
      "group": "DT New",
      "mc": "DT 13",
      "jenis": "D",
      "plan": "",
      "doff": "00:00",
      "start": "00:15",
      "code": "",
      "std": "13.5",
      "dt_mc": "15",
      "dt_proc": "10",
      "loss": "3.5",
      "pct_loss": "0.7%",
      "overlap": "220",
      "ket": "D+C+HB",
      "status": "Actual",
      "eff": "25.7%"
    },
    {
      "key": "20260723-NS-DT 13-PLAN",
      "date": "7/23/2026",
      "shift": "",
      "cluster": "CM3",
      "group": "DT New",
      "mc": "DT 13",
      "jenis": "D",
      "plan": "",
      "doff": "",
      "start": "00:15",
      "code": "",
      "std": "13.5",
      "dt_mc": "15",
      "dt_proc": "10",
      "loss": "3.5",
      "pct_loss": "0.7%",
      "overlap": "220",
      "ket": "D + C + HB",
      "status": "Plan",
      "eff": "25.7%"
    },
    {
      "key": "20260723-NS-DT 10-PLAN",
      "date": "7/23/2026",
      "shift": "",
      "cluster": "CM3",
      "group": "DT New",
      "mc": "DT 10",
      "jenis": "GF",
      "plan": "23:55",
      "doff": "23:55",
      "start": "01:10",
      "code": "",
      "std": "82.7",
      "dt_mc": "",
      "dt_proc": "",
      "loss": "",
      "pct_loss": "",
      "overlap": "295",
      "ket": "D+GF",
      "status": "Actual",
      "eff": ""
    },
    {
      "key": "20260723-NS-DT 10-PLAN",
      "date": "7/23/2026",
      "shift": "",
      "cluster": "CM3",
      "group": "DT New",
      "mc": "DT 10",
      "jenis": "GF",
      "plan": "23:55",
      "doff": "23:55",
      "start": "01:10",
      "code": "",
      "std": "82.7",
      "dt_mc": "",
      "dt_proc": "",
      "loss": "",
      "pct_loss": "",
      "overlap": "295",
      "ket": "D+ GF",
      "status": "Plan",
      "eff": ""
    },
    {
      "key": "20260723-NS-DT 8-PLAN",
      "date": "7/23/2026",
      "shift": "",
      "cluster": "CM3",
      "group": "DT New",
      "mc": "DT 8",
      "jenis": "D",
      "plan": "02:10",
      "doff": "02:10",
      "start": "02:25",
      "code": "",
      "std": "13.5",
      "dt_mc": "15",
      "dt_proc": "15",
      "loss": "-1.5",
      "pct_loss": "-0.3%",
      "overlap": "",
      "ket": "D+C+HB",
      "status": "Actual",
      "eff": "-11.5%"
    },
    {
      "key": "20260723-NS-DT 8-PLAN",
      "date": "7/23/2026",
      "shift": "",
      "cluster": "CM3",
      "group": "DT New",
      "mc": "DT 8",
      "jenis": "D",
      "plan": "02:10",
      "doff": "02:10",
      "start": "02:25",
      "code": "",
      "std": "13.5",
      "dt_mc": "15",
      "dt_proc": "15",
      "loss": "-1.5",
      "pct_loss": "-0.3%",
      "overlap": "115",
      "ket": "D + C + HB",
      "status": "Plan",
      "eff": "-11.5%"
    },
    {
      "key": "20260723-NS-DT 12-PLAN",
      "date": "7/23/2026",
      "shift": "",
      "cluster": "CM3",
      "group": "DT New",
      "mc": "DT 12",
      "jenis": "GF",
      "plan": "02:30",
      "doff": "02:30",
      "start": "03:40",
      "code": "",
      "std": "82.7",
      "dt_mc": "70",
      "dt_proc": "70",
      "loss": "12.7",
      "pct_loss": "2.7%",
      "overlap": "",
      "ket": "D+GF",
      "status": "Actual",
      "eff": "15.4%"
    },
    {
      "key": "20260723-NS-DT 12-PLAN",
      "date": "7/23/2026",
      "shift": "",
      "cluster": "CM3",
      "group": "DT New",
      "mc": "DT 12",
      "jenis": "GF",
      "plan": "02:30",
      "doff": "02:30",
      "start": "03:40",
      "code": "",
      "std": "82.7",
      "dt_mc": "70",
      "dt_proc": "70",
      "loss": "12.7",
      "pct_loss": "2.7%",
      "overlap": "",
      "ket": "D + C + HB",
      "status": "Plan",
      "eff": "15.4%"
    },
    {
      "key": "20260723-NS-DT 9-PLAN",
      "date": "7/23/2026",
      "shift": "",
      "cluster": "CM3",
      "group": "DT New",
      "mc": "DT 9",
      "jenis": "GF",
      "plan": "03:00",
      "doff": "03:00",
      "start": "04:50",
      "code": "",
      "std": "82.7",
      "dt_mc": "110",
      "dt_proc": "70",
      "loss": "12.7",
      "pct_loss": "2.7%",
      "overlap": "",
      "ket": "D+GF 3/4 + dahulukan dt 12",
      "status": "Actual",
      "eff": "15.4%"
    },
    {
      "key": "20260723-NS-DT 9-PLAN",
      "date": "7/23/2026",
      "shift": "",
      "cluster": "CM3",
      "group": "DT New",
      "mc": "DT 9",
      "jenis": "GF",
      "plan": "03:00",
      "doff": "03:00",
      "start": "04:50",
      "code": "",
      "std": "82.72727273",
      "dt_mc": "110",
      "dt_proc": "70",
      "loss": "12.7",
      "pct_loss": "2.7%",
      "overlap": "",
      "ket": "D + C + HB + GF 3/4 dah 12",
      "status": "Plan",
      "eff": "15.4%"
    },
    {
      "key": "20260723-NS-DT 11-PLAN",
      "date": "7/23/2026",
      "shift": "",
      "cluster": "CM3",
      "group": "DT New",
      "mc": "DT 11",
      "jenis": "GF",
      "plan": "22:00",
      "doff": "",
      "start": "",
      "code": "",
      "std": "82.72727273",
      "dt_mc": "",
      "dt_proc": "",
      "loss": "",
      "pct_loss": "",
      "overlap": "",
      "ket": "MC Stop",
      "status": "Plan",
      "eff": ""
    },
    {
      "key": "20260723-NS-L 15-PLAN",
      "date": "7/23/2026",
      "shift": "",
      "cluster": "CM3",
      "group": "NL",
      "mc": "L 15",
      "jenis": "GF",
      "plan": "01:00",
      "doff": "23:30",
      "start": "01:00",
      "code": "",
      "std": "35.78571429",
      "dt_mc": "90",
      "dt_proc": "90",
      "loss": "-54.2",
      "pct_loss": "-11.3%",
      "overlap": "35",
      "ket": "D+ GF + Tunggu Feeding",
      "status": "Actual",
      "eff": "-151.5%"
    },
    {
      "key": "20260723-NS-L 18-PLAN",
      "date": "7/23/2026",
      "shift": "",
      "cluster": "CM3",
      "group": "NL",
      "mc": "L 18",
      "jenis": "GF",
      "plan": "04:00",
      "doff": "03:00",
      "start": "04:00",
      "code": "",
      "std": "35.78571429",
      "dt_mc": "60",
      "dt_proc": "60",
      "loss": "-24.2",
      "pct_loss": "-5.0%",
      "overlap": "",
      "ket": "D+ GF + Tunggu Feeding",
      "status": "Actual",
      "eff": "-67.7%"
    },
    {
      "key": "20260723-NS-Delta 1-PLAN",
      "date": "7/23/2026",
      "shift": "NS",
      "cluster": "CM6",
      "group": "TBR Delta",
      "mc": "Delta 1",
      "jenis": "GF",
      "plan": "22:50",
      "doff": "22:50",
      "start": "00:00",
      "code": "",
      "std": "37.1",
      "dt_mc": "70",
      "dt_proc": "70",
      "loss": "-33.0",
      "pct_loss": "-6.9%",
      "overlap": "230",
      "ket": "Doff + gf + R",
      "status": "Actual",
      "eff": "-88.9%"
    },
    {
      "key": "20260723-NS-Delta 10-PLAN",
      "date": "7/23/2026",
      "shift": "NS",
      "cluster": "CM6",
      "group": "TBR Delta",
      "mc": "Delta 10",
      "jenis": "GF",
      "plan": "05:00",
      "doff": "04:45",
      "start": "05:20",
      "code": "",
      "std": "37.1",
      "dt_mc": "35",
      "dt_proc": "35",
      "loss": "2.1",
      "pct_loss": "0.4%",
      "overlap": "",
      "ket": "Doff + gf + R",
      "status": "Actual",
      "eff": "5.5%"
    },
    {
      "key": "20260723-NS-DT 4-PLAN",
      "date": "7/23/2026",
      "shift": "NS",
      "cluster": "CM6",
      "group": "TBR DT",
      "mc": "DT 4",
      "jenis": "GF",
      "plan": "22:00",
      "doff": "22:00",
      "start": "00:25",
      "code": "",
      "std": "82.7",
      "dt_mc": "145",
      "dt_proc": "145",
      "loss": "-62.3",
      "pct_loss": "-13.0%",
      "overlap": "160",
      "ket": "D+GF+BRIEFING+PAT AWAL+G .TENSIONER",
      "status": "Actual",
      "eff": "-75.3%"
    },
    {
      "key": "20260723-NS-DT 3-PLAN",
      "date": "7/23/2026",
      "shift": "NS",
      "cluster": "CM6",
      "group": "TBR DT",
      "mc": "DT 3",
      "jenis": "D",
      "plan": "22:00",
      "doff": "22:00",
      "start": "00:40",
      "code": "REP",
      "std": "13.5",
      "dt_mc": "160",
      "dt_proc": "",
      "loss": "",
      "pct_loss": "",
      "overlap": "320",
      "ket": "",
      "status": "Actual",
      "eff": ""
    },
    {
      "key": "20260723-NS-DT 6-PLAN",
      "date": "7/23/2026",
      "shift": "NS",
      "cluster": "CM6",
      "group": "TBR DT",
      "mc": "DT 6",
      "jenis": "D",
      "plan": "01:50",
      "doff": "01:50",
      "start": "02:40",
      "code": "",
      "std": "13.5",
      "dt_mc": "50",
      "dt_proc": "50",
      "loss": "-36.5",
      "pct_loss": "-7.6%",
      "overlap": "",
      "ket": "D+C+HB (10) + PERG ISTIRAHAT",
      "status": "Actual",
      "eff": "-271.6%"
    },
    {
      "key": "20260723-NS-DT 1-PLAN",
      "date": "7/23/2026",
      "shift": "NS",
      "cluster": "CM6",
      "group": "TBR DT",
      "mc": "DT 1",
      "jenis": "D",
      "plan": "02:50",
      "doff": "02:50",
      "start": "03:20",
      "code": "",
      "std": "13.5",
      "dt_mc": "30",
      "dt_proc": "30",
      "loss": "-16.5",
      "pct_loss": "-3.4%",
      "overlap": "190",
      "ket": "D+C+HB(12)",
      "status": "Actual",
      "eff": "-123.0%"
    },
    {
      "key": "20260723-NS-L 1-PLAN",
      "date": "7/23/2026",
      "shift": "NS",
      "cluster": "CM6",
      "group": "TBR L",
      "mc": "L 1",
      "jenis": "GF",
      "plan": "23:40",
      "doff": "22:50",
      "start": "23:30",
      "code": "",
      "std": "35.8",
      "dt_mc": "40",
      "dt_proc": "40",
      "loss": "-4.2",
      "pct_loss": "-0.9%",
      "overlap": "",
      "ket": "GF",
      "status": "Actual",
      "eff": "-11.8%"
    },
    {
      "key": "20260723-NS-L 7-PLAN",
      "date": "7/23/2026",
      "shift": "NS",
      "cluster": "CM6",
      "group": "TBR L",
      "mc": "L 7",
      "jenis": "GF",
      "plan": "04:00",
      "doff": "02:50",
      "start": "03:30",
      "code": "",
      "std": "35.8",
      "dt_mc": "40",
      "dt_proc": "40",
      "loss": "-4.2",
      "pct_loss": "-0.9%",
      "overlap": "55",
      "ket": "D+gf",
      "status": "Actual",
      "eff": "-11.8%"
    },
    {
      "key": "20260723-NS-L 5-PLAN",
      "date": "7/23/2026",
      "shift": "NS",
      "cluster": "CM6",
      "group": "TBR L",
      "mc": "L 5",
      "jenis": "GF",
      "plan": "22:15",
      "doff": "22:15",
      "start": "03:45",
      "code": "",
      "std": "35.8",
      "dt_mc": "330",
      "dt_proc": "15",
      "loss": "20.8",
      "pct_loss": "4.3%",
      "overlap": "445",
      "ket": "D +hp ke 275/3 + test QA ok 03:15",
      "status": "Actual",
      "eff": "58.1%"
    },
    {
      "key": "20260723-NS-L 2-PLAN",
      "date": "7/23/2026",
      "shift": "NS",
      "cluster": "CM6",
      "group": "TBR L",
      "mc": "L 2",
      "jenis": "GF",
      "plan": "04:00",
      "doff": "03:50",
      "start": "04:10",
      "code": "",
      "std": "35.8",
      "dt_mc": "20",
      "dt_proc": "20",
      "loss": "15.8",
      "pct_loss": "3.3%",
      "overlap": "90",
      "ket": "D+gf",
      "status": "Actual",
      "eff": "44.1%"
    },
    {
      "key": "20260723-NS-L 4-PLAN",
      "date": "7/23/2026",
      "shift": "NS",
      "cluster": "CM6",
      "group": "TBR L",
      "mc": "L 4",
      "jenis": "GF",
      "plan": "02:40",
      "doff": "02:40",
      "start": "05:40",
      "code": "",
      "std": "35.8",
      "dt_mc": "180",
      "dt_proc": "90",
      "loss": "-54.2",
      "pct_loss": "-11.3%",
      "overlap": "",
      "ket": "D+ hp ke 275/3 changsu Test QA ok jam 05:00",
      "status": "Actual",
      "eff": "-151.5%"
    },
    {
      "key": "20260723-NS-L 9-PLAN",
      "date": "7/23/2026",
      "shift": "NS",
      "cluster": "CM6",
      "group": "TBR L",
      "mc": "L 9",
      "jenis": "GF",
      "plan": "05:45",
      "doff": "05:45",
      "start": "06:00",
      "code": "L",
      "std": "35.8",
      "dt_mc": "15",
      "dt_proc": "",
      "loss": "",
      "pct_loss": "",
      "overlap": "",
      "ket": "",
      "status": "Plan",
      "eff": ""
    }
  ]
}